setup.py
moody_harshit/__init__.py
moody_harshit.egg-info/PKG-INFO
moody_harshit.egg-info/SOURCES.txt
moody_harshit.egg-info/dependency_links.txt
moody_harshit.egg-info/top_level.txt