Metadata-Version: 1.0
Name: moody-harshit
Version: 0.0.1
Summary: a pip-installable package example
Home-page: https://github.com/bgse/hellostackoverflow
Author: Harshit
Author-email: harshitagarwal37@gmail.com
License: UNKNOWN
Keywords: example
Platform: UNKNOWN
